[{"name":"htmlwidgets","version":"1.6.4","src":{"file":"www"},"meta":null,"script":"htmlwidgets.js","stylesheet":null,"head":null,"attachment":null,"package":"htmlwidgets","all_files":true},{"name":"d3","version":"4.5.0","src":{"file":"htmlwidgets\/lib\/d3-4.5.0"},"meta":null,"script":"d3.min.js","stylesheet":null,"head":null,"attachment":null,"package":"networkD3","all_files":true},{"name":"diagonalNetwork-binding","version":"0.4","src":{"file":"htmlwidgets"},"meta":null,"script":"diagonalNetwork.js","stylesheet":null,"head":null,"attachment":null,"package":"networkD3","all_files":false}]
